setup.cfg
setup.py
creaturecast_nodegraph/__init__.py
creaturecast_nodegraph/__main__.py
creaturecast_nodegraph.egg-info/PKG-INFO
creaturecast_nodegraph.egg-info/SOURCES.txt
creaturecast_nodegraph.egg-info/dependency_links.txt
creaturecast_nodegraph.egg-info/requires.txt
creaturecast_nodegraph.egg-info/top_level.txt
creaturecast_nodegraph/media/__init__.py
creaturecast_nodegraph/media/fonts/__init__.py
creaturecast_nodegraph/media/icons/__init__.py
creaturecast_nodegraph/services/__init__.py
creaturecast_nodegraph/services/get_image.py
creaturecast_nodegraph/services/get_stylesheet.py
creaturecast_nodegraph/services/thread_worker.py
creaturecast_nodegraph/widgets/__init__.py
creaturecast_nodegraph/widgets/icon.py
creaturecast_nodegraph/widgets/node_graph_widget.py
creaturecast_nodegraph/widgets/graphics_item/__init__.py
creaturecast_nodegraph/widgets/graphics_item/knob.py
creaturecast_nodegraph/widgets/graphics_item/node.py